oidc_client/__init__.py
oidc_client/__main__.py
oidc_client/cli.py
oidc_client/config.py
oidc_client/discovery.py
oidc_client/error.py
oidc_client/index.html
oidc_client/lib.py
oidc_client/localhost.crt
oidc_client/localhost.key
oidc_client/oauth.py
oidc_client/pkce.py
oidc_client/py.typed
oidc_client/tls.py
oidc_client-0.2.6.dist-info/LICENSE.md
oidc_client-0.2.6.dist-info/METADATA
oidc_client-0.2.6.dist-info/WHEEL
oidc_client-0.2.6.dist-info/entry_points.txt
oidc_client-0.2.6.dist-info/RECORD
