Metadata-Version: 2.1
Name: oidc-client
Version: 0.2.6
Summary: A pure-Python OpenID Connect client
Home-page: https://gitlab.com/lzinsou/oidc-client
Keywords: openid,oidc,oauth,oauth2
Author: Loris Zinsou
Author-email: lzinsou@proton.me
Requires-Python: >=3.10,<4.0
Classifier: Development Status :: 4 - Beta
Classifier: Environment :: Console
Classifier: Programming Language :: Python :: 3
Classifier: Programming Language :: Python :: 3.10
Classifier: Programming Language :: Python :: 3.11
Classifier: Topic :: Internet :: WWW/HTTP
Requires-Dist: StrEnum (>=0.4) ; python_version < "3.11"
Requires-Dist: toml (>=0.10) ; python_version < "3.11"
Project-URL: Repository, https://gitlab.com/lzinsou/oidc-client
